HISTORY.rst
LICENSE
MANIFEST.in
README.rst
setup.cfg
setup.py
tox.ini
features/act-action.feature
features/act-hyperlink.feature
features/cht-axis-props.feature
features/cht-axistitle-props.feature
features/cht-category-access.feature
features/cht-category-props.feature
features/cht-chart.feature
features/cht-charttitle-props.feature
features/cht-data-props.feature
features/cht-datalabels.feature
features/cht-gridlines-props.feature
features/cht-legend-access.feature
features/cht-legend-props.feature
features/cht-marker-props.feature
features/cht-plot-props.feature
features/cht-point-access.feature
features/cht-point-props.feature
features/cht-replace-data.feature
features/cht-series.feature
features/cht-ticklabels-props.feature
features/dml-color.feature
features/dml-effect.feature
features/dml-fill.feature
features/dml-line.feature
features/environment.py
features/ph-inherit-props.feature
features/ph-insert-shape.feature
features/ph-phfmt-props.feature
features/ph-placeholder-props.feature
features/prs-coreprops.feature
features/prs-default-template.feature
features/prs-open-save.feature
features/prs-presentation-props.feature
features/shp-autoshape.feature
features/shp-connector.feature
features/shp-freeform.feature
features/shp-graphicframe.feature
features/shp-groupshape.feature
features/shp-movie-props.feature
features/shp-picture.feature
features/shp-placeholder.feature
features/shp-shapes.feature
features/shp-shared.feature
features/sld-background.feature
features/sld-slide.feature
features/sld-slides.feature
features/tbl-cell.feature
features/tbl-column.feature
features/tbl-table.feature
features/txt-fit-text.feature
features/txt-font-color.feature
features/txt-font-props.feature
features/txt-paragraph.feature
features/txt-text.feature
features/txt-textframe.feature
features/_scratch/test_out.pptx
features/steps/action.py
features/steps/axis.py
features/steps/background.py
features/steps/category.py
features/steps/chart.py
features/steps/chartdata.py
python_pptx_fix.egg-info/PKG-INFO
python_pptx_fix.egg-info/SOURCES.txt
python_pptx_fix.egg-info/dependency_links.txt
python_pptx_fix.egg-info/not-zip-safe
python_pptx_fix.egg-info/requires.txt
python_pptx_fix.egg-info/top_level.txt
