Metadata-Version: 2.1
Name: python-pptx-fix
Version: 0.6.21.1
Summary: Generate and manipulate Open XML PowerPoint (.pptx) files
Home-page: https://github.com/kascodeo/python-pptx
Author: Steve Canny
Author-email: python-pptx@googlegroups.com
Maintainer: Karim
Maintainer-email: kascodeo@gmail.com
License: The MIT License (MIT)
Keywords: python-pptx python-pptx-fix fix powerpoint ppt pptx office open xml
Classifier: Development Status :: 4 - Beta
Classifier: Environment :: Console
Classifier: Intended Audience :: Developers
Classifier: License :: OSI Approved :: MIT License
Classifier: Operating System :: OS Independent
Classifier: Programming Language :: Python
Classifier: Programming Language :: Python :: 2
Classifier: Programming Language :: Python :: 2.7
Classifier: Programming Language :: Python :: 3
Classifier: Programming Language :: Python :: 3.6
Classifier: Topic :: Office/Business :: Office Suites
Classifier: Topic :: Software Development :: Libraries
License-File: LICENSE
